{"chunk_definitions":[{"row":14,"row_count":1,"visible":true,"expansion_state":0,"options":{"engine":"r","message":false,"warning":false,"label":"unnamed-chunk-9"},"document_id":"B9367DEC","chunk_id":"cokm8cdk70wx4","chunk_label":"unnamed-chunk-1"},{"row":19,"row_count":1,"visible":true,"expansion_state":0,"options":{"engine":"r","label":"unnamed-chunk-10"},"document_id":"B9367DEC","chunk_id":"cv3yk1n2woxft","chunk_label":"unnamed-chunk-2"},{"row":39,"row_count":1,"visible":true,"expansion_state":0,"options":{"engine":"r","label":"unnamed-chunk-11"},"document_id":"B9367DEC","chunk_id":"ctfa3fshi65y6","chunk_label":"unnamed-chunk-3"},{"row":57,"row_count":1,"visible":true,"expansion_state":0,"options":{"engine":"r","label":"unnamed-chunk-25"},"document_id":"B9367DEC","chunk_id":"ca0emeaqipa07","chunk_label":"unnamed-chunk-4"},{"row":70,"row_count":1,"visible":true,"expansion_state":0,"options":{"engine":"r","label":"unnamed-chunk-26"},"document_id":"B9367DEC","chunk_id":"cbv0eyvlisc7c","chunk_label":"unnamed-chunk-5"}],"doc_write_time":1651327146,"chunk_rendered_width":653}